[
  {
    "id": "2d2a3bb6-6d59-4392-8ca2-cccb23de2dbf",
    "data": [
      {
        "text": "Quiero",
        "meta": "@sys.ignore",
        "userDefined": false
      },
      {
        "text": " ver ",
        "userDefined": false
      },
      {
        "text": "mi",
        "meta": "@sys.ignore",
        "userDefined": false
      },
      {
        "text": " lista de competiciones favoritas",
        "userDefined": false
      }
    ],
    "isTemplate": false,
    "count": 0,
    "lang": "es",
    "updated": 0
  },
  {
    "id": "68edbae4-9151-4d08-afde-3be96e96e888",
    "data": [
      {
        "text": "Enséñame ",
        "userDefined": false
      },
      {
        "text": "mi",
        "meta": "@sys.ignore",
        "userDefined": false
      },
      {
        "text": " lista de competiciones favoritas",
        "userDefined": false
      }
    ],
    "isTemplate": false,
    "count": 0,
    "lang": "es",
    "updated": 0
  },
  {
    "id": "af465564-1699-40ff-ab6d-4b4419ed9a40",
    "data": [
      {
        "text": "Deseo",
        "meta": "@sys.ignore",
        "userDefined": false
      },
      {
        "text": " ver ",
        "userDefined": false
      },
      {
        "text": "mi",
        "meta": "@sys.ignore",
        "userDefined": false
      },
      {
        "text": " lista de competiciones favoritas",
        "userDefined": false
      }
    ],
    "isTemplate": false,
    "count": 0,
    "lang": "es",
    "updated": 0
  },
  {
    "id": "1bce8e71-77e6-42ad-83d0-b0e4bc34131e",
    "data": [
      {
        "text": "Listar",
        "meta": "@sys.ignore",
        "userDefined": false
      },
      {
        "text": " ",
        "userDefined": false
      },
      {
        "text": "mis",
        "meta": "@sys.ignore",
        "userDefined": false
      },
      {
        "text": " competiciones favoritas",
        "userDefined": false
      }
    ],
    "isTemplate": false,
    "count": 0,
    "lang": "es",
    "updated": 0
  },
  {
    "id": "4db99598-9a54-40ec-97d1-01b3de9d5368",
    "data": [
      {
        "text": "Lista",
        "meta": "@sys.ignore",
        "userDefined": false
      },
      {
        "text": " de ",
        "userDefined": false
      },
      {
        "text": "competiciones favoritas",
        "meta": "@sys.ignore",
        "userDefined": false
      }
    ],
    "isTemplate": false,
    "count": 0,
    "lang": "es",
    "updated": 0
  }
]